call518_test_pkg/__init__.py
call518_test_pkg/py.typed
call518_test_pkg-0.1.0.dist-info/METADATA
call518_test_pkg-0.1.0.dist-info/WHEEL
call518_test_pkg-0.1.0.dist-info/RECORD
