Metadata-Version: 2.4
Name: call518-test-pkg
Version: 0.1.0
Summary: Add your description here
Author-email: JungJungIn <call518@gmail.com>
Requires-Python: >=3.11
Requires-Dist: requests>=2.32.4
